netscanner/__init__.py
netscanner/__main__.py
netscanner-0.1.1.dist-info/LICENSE.md
netscanner-0.1.1.dist-info/WHEEL
netscanner-0.1.1.dist-info/METADATA
netscanner-0.1.1.dist-info/RECORD
