Metadata-Version: 2.1
Name: netscanner
Version: 0.1.1
Summary: A comprehensive network reconnaissance tool
Home-page: https://github.com/add0242/NETSCANNER
Author: Adam Dawood
Author-email: ADD0242@MY.LONDONMET.AC.UK
Classifier: Programming Language :: Python :: 2
Classifier: Programming Language :: Python :: 2.7
Classifier: Programming Language :: Python :: 3
Classifier: Programming Language :: Python :: 3.4
Classifier: Programming Language :: Python :: 3.5
Classifier: Programming Language :: Python :: 3.6
Classifier: Programming Language :: Python :: 3.7
Classifier: Programming Language :: Python :: 3.8
Classifier: Programming Language :: Python :: 3.9
Classifier: Programming Language :: Python :: 3.10
Classifier: Programming Language :: Python :: 3.11
Requires-Dist: mac-vendor-lookup (>=0.1.12,<0.2.0)
Project-URL: Repository, https://github.com/add0242/NETSCANNER
